virtual_anomaly/__init__.py
virtual_anomaly/add_spike.py
virtual_anomaly/delay_part.py
virtual_anomaly/flood_signal.py
virtual_anomaly-0.1.4.dist-info/METADATA
virtual_anomaly-0.1.4.dist-info/WHEEL
virtual_anomaly-0.1.4.dist-info/RECORD
