Metadata-Version: 2.1
Name: virtual-anomaly
Version: 0.1.4
Summary: A python package for making virtual anomalies in one dimensional data.
License: MIT
Author: Yacine Bel-Hadj
Author-email: yacine.bel-hadj@vub.be
Requires-Python: >=3.8,<4.0
Classifier: License :: OSI Approved :: MIT License
Classifier: Programming Language :: Python :: 3
Classifier: Programming Language :: Python :: 3.8
Classifier: Programming Language :: Python :: 3.9
Classifier: Programming Language :: Python :: 3.10
Classifier: Programming Language :: Python :: 3.11
Classifier: Programming Language :: Python :: 3.12
Requires-Dist: torch (>=2.0.0,<3.0.0)
